foldkit/__init__.py
foldkit/af3_result.py
foldkit/cli.py
foldkit/storage.py
foldkit-0.1.2.dist-info/licenses/LICENSE
foldkit-0.1.2.dist-info/METADATA
foldkit-0.1.2.dist-info/WHEEL
foldkit-0.1.2.dist-info/entry_points.txt
foldkit-0.1.2.dist-info/top_level.txt
foldkit-0.1.2.dist-info/RECORD
