Metadata-Version: 2.4
Name: foldkit
Version: 0.1.2
Summary: Toolkit for working with AlphaFold3 results and confidence metadata
Author-email: Jonathan Levine <jonalevine1@gmail.com>
License: MIT
Keywords: protein,protein design,alphafold,bioinformatics
Classifier: Programming Language :: Python :: 3
Classifier: License :: OSI Approved :: MIT License
Classifier: Operating System :: OS Independent
Requires-Python: >=3.9
License-File: LICENSE
Requires-Dist: numpy
Requires-Dist: biopython
Requires-Dist: tqdm
Dynamic: license-file
